odoo_mcp/__init__.py
odoo_mcp/__main__.py
odoo_mcp/odoo_client.py
odoo_mcp/server.py
odoo_mcp_xyt-2.4.0.2.dist-info/licenses/LICENSE
odoo_mcp_xyt-2.4.0.2.dist-info/METADATA
odoo_mcp_xyt-2.4.0.2.dist-info/WHEEL
odoo_mcp_xyt-2.4.0.2.dist-info/entry_points.txt
odoo_mcp_xyt-2.4.0.2.dist-info/top_level.txt
odoo_mcp_xyt-2.4.0.2.dist-info/RECORD
